jupyter_mindmaps/Templates/apod.j2
jupyter_mindmaps/Templates/cme.j2
jupyter_mindmaps/Templates/epicNat.j2
jupyter_mindmaps/Templates/events.j2
jupyter_mindmaps/Templates/flr.j2
jupyter_mindmaps/Templates/gst.j2
jupyter_mindmaps/Templates/hss.j2
jupyter_mindmaps/Templates/ips.j2
jupyter_mindmaps/Templates/iss.j2
jupyter_mindmaps/Templates/knownCount.j2
jupyter_mindmaps/Templates/mpc.j2
jupyter_mindmaps/Templates/natural.j2
jupyter_mindmaps/Templates/neo.j2
jupyter_mindmaps/Templates/notification.j2
jupyter_mindmaps/Templates/people.j2
jupyter_mindmaps/Templates/planets.j2
jupyter_mindmaps/Templates/rbe.j2
jupyter_mindmaps/Templates/sep.j2
jupyter_mindmaps/Templates/space.j2
jupyter_mindmaps/Templates/weatherOnMars.j2
jupyter_mindmaps/Templates/wsa.j2
jupyter_mindmaps/__init__.py
jupyter_mindmaps/jupyter_mindmaps.py
jupyter_mindmaps/script.py
jupyter_mindmaps-1.1.1.dist-info/entry_points.txt
jupyter_mindmaps-1.1.1.dist-info/LICENSE
jupyter_mindmaps-1.1.1.dist-info/WHEEL
jupyter_mindmaps-1.1.1.dist-info/METADATA
jupyter_mindmaps-1.1.1.dist-info/RECORD
