Metadata-Version: 2.1
Name: jupyter-mindmaps
Version: 1.1.1
Summary: Mindamps of Space
Author: John Capobianco
Author-email: ptcapo@gmail.com
Requires-Python: >=3.8,<4.0
Classifier: Programming Language :: Python :: 3
Classifier: Programming Language :: Python :: 3.10
Classifier: Programming Language :: Python :: 3.8
Classifier: Programming Language :: Python :: 3.9
Requires-Dist: Jinja2 (>=3.1.2,<4.0.0)
Requires-Dist: requests (>=2.28.1,<3.0.0)
Requires-Dist: rich-click (>=1.5.2,<2.0.0)
